[
    {
        "createdBy": 34,
        "createdDate": "2025-05-20T05:56:03.000+0000",
        "documentKey": "SJ_cms-CMP-1",
        "fields": {
            "documentKey": "SJ_cms-CMP-1",
            "globalId": "GID-85589",
            "name": "ステークフォルダー要求",
            "relase$30": 198
        },
        "globalId": "GID-85589",
        "id": 199883,
        "itemType": 30,
        "lastActivityDate": "2025-05-20T05:56:03.000+0000",
        "location": {
            "globalSortOrder": 1073742359,
            "parent": {
                "project": 186
            },
            "sequence": "1",
            "sortOrder": 0
        },
        "lock": {
            "locked": false
        },
        "modifiedBy": 34,
        "modifiedDate": "2025-05-20T05:56:03.000+0000",
        "project": 186,
        "resources": {
            "self": {
                "allowed": [
                    "GET",
                    "PUT",
                    "PATCH",
                    "DELETE"
                ]
            }
        },
        "type": "items",
        "version": 1
    }
]